smack/__init__.py
smack/smack.py
smack-0.2.4.dist-info/LICENSE
smack-0.2.4.dist-info/METADATA
smack-0.2.4.dist-info/WHEEL
smack-0.2.4.dist-info/entry_points.txt
smack-0.2.4.dist-info/top_level.txt
smack-0.2.4.dist-info/RECORD
