Metadata-Version: 2.1
Name: smack
Version: 0.2.4
Summary: Creates a basic folder structure for PyPi projects
Author-email: Jacen Fossey <jhfossey@fossey.ca>
Project-URL: Homepage, https://github.com/JacenFossey/smack
Project-URL: Bug Tracker, https://github.com/JacenFossey/smack/issues
Classifier: Programming Language :: Python :: 3
Classifier: License :: OSI Approved :: MIT License
Classifier: Operating System :: OS Independent
Requires-Python: >=3.7
License-File: LICENSE
Requires-Dist: click
